{
  "algorithm": "two-bit",
  "trace_file": "exchange2",
  "runs": [
    {
      "max_lines": 1000,
      "stats": [
        {
          "config": {
            "table_size": 512,
            "initial_state": "StronglyNotTaken"
          },
          "result": {
            "mispredictions": 108,
            "count": 949,
            "correct": 841,
            "accuracy": "88.62%",
            "misprediction_rate": "11.38%"
          }
        },
        {
          "config": {
            "table_size": 512,
            "initial_state": "WeaklyNotTaken"
          },
          "result": {
            "mispredictions": 100,
            "count": 949,
            "correct": 849,
            "accuracy": "89.46%",
            "misprediction_rate": "10.54%"
          }
        },
        {
          "config": {
            "table_size": 512,
            "initial_state": "WeaklyTaken"
          },
          "result": {
            "mispredictions": 129,
            "count": 949,
            "correct": 820,
            "accuracy": "86.41%",
            "misprediction_rate": "13.59%"
          }
        },
        {
          "config": {
            "table_size": 512,
            "initial_state": "StronglyTaken"
          },
          "result": {
            "mispredictions": 145,
            "count": 949,
            "correct": 804,
            "accuracy": "84.72%",
            "misprediction_rate": "15.28%"
          }
        },
        {
          "config": {
            "table_size": 1024,
            "initial_state": "StronglyNotTaken"
          },
          "result": {
            "mispredictions": 108,
            "count": 949,
            "correct": 841,
            "accuracy": "88.62%",
            "misprediction_rate": "11.38%"
          }
        },
        {
          "config": {
            "table_size": 1024,
            "initial_state": "WeaklyNotTaken"
          },
          "result": {
            "mispredictions": 98,
            "count": 949,
            "correct": 851,
            "accuracy": "89.67%",
            "misprediction_rate": "10.33%"
          }
        },
        {
          "config": {
            "table_size": 1024,
            "initial_state": "WeaklyTaken"
          },
          "result": {
            "mispredictions": 126,
            "count": 949,
            "correct": 823,
            "accuracy": "86.72%",
            "misprediction_rate": "13.28%"
          }
        },
        {
          "config": {
            "table_size": 1024,
            "initial_state": "StronglyTaken"
          },
          "result": {
            "mispredictions": 143,
            "count": 949,
            "correct": 806,
            "accuracy": "84.93%",
            "misprediction_rate": "15.07%"
          }
        },
        {
          "config": {
            "table_size": 2048,
            "initial_state": "StronglyNotTaken"
          },
          "result": {
            "mispredictions": 108,
            "count": 949,
            "correct": 841,
            "accuracy": "88.62%",
            "misprediction_rate": "11.38%"
          }
        },
        {
          "config": {
            "table_size": 2048,
            "initial_state": "WeaklyNotTaken"
          },
          "result": {
            "mispredictions": 98,
            "count": 949,
            "correct": 851,
            "accuracy": "89.67%",
            "misprediction_rate": "10.33%"
          }
        },
        {
          "config": {
            "table_size": 2048,
            "initial_state": "WeaklyTaken"
          },
          "result": {
            "mispredictions": 128,
            "count": 949,
            "correct": 821,
            "accuracy": "86.51%",
            "misprediction_rate": "13.49%"
          }
        },
        {
          "config": {
            "table_size": 2048,
            "initial_state": "StronglyTaken"
          },
          "result": {
            "mispredictions": 143,
            "count": 949,
            "correct": 806,
            "accuracy": "84.93%",
            "misprediction_rate": "15.07%"
          }
        },
        {
          "config": {
            "table_size": 4096,
            "initial_state": "StronglyNotTaken"
          },
          "result": {
            "mispredictions": 108,
            "count": 949,
            "correct": 841,
            "accuracy": "88.62%",
            "misprediction_rate": "11.38%"
          }
        },
        {
          "config": {
            "table_size": 4096,
            "initial_state": "WeaklyNotTaken"
          },
          "result": {
            "mispredictions": 98,
            "count": 949,
            "correct": 851,
            "accuracy": "89.67%",
            "misprediction_rate": "10.33%"
          }
        },
        {
          "config": {
            "table_size": 4096,
            "initial_state": "WeaklyTaken"
          },
          "result": {
            "mispredictions": 128,
            "count": 949,
            "correct": 821,
            "accuracy": "86.51%",
            "misprediction_rate": "13.49%"
          }
        },
        {
          "config": {
            "table_size": 4096,
            "initial_state": "StronglyTaken"
          },
          "result": {
            "mispredictions": 143,
            "count": 949,
            "correct": 806,
            "accuracy": "84.93%",
            "misprediction_rate": "15.07%"
          }
        }
      ]
    },
    {
      "max_lines": 10000,
      "stats": [
        {
          "config": {
            "table_size": 512,
            "initial_state": "StronglyNotTaken"
          },
          "result": {
            "mispredictions": 1444,
            "count": 8431,
            "correct": 6987,
            "accuracy": "82.87%",
            "misprediction_rate": "17.13%"
          }
        },
        {
          "config": {
            "table_size": 512,
            "initial_state": "WeaklyNotTaken"
          },
          "result": {
            "mispredictions": 1438,
            "count": 8431,
            "correct": 6993,
            "accuracy": "82.94%",
            "misprediction_rate": "17.06%"
          }
        },
        {
          "config": {
            "table_size": 512,
            "initial_state": "WeaklyTaken"
          },
          "result": {
            "mispredictions": 1566,
            "count": 8431,
            "correct": 6865,
            "accuracy": "81.43%",
            "misprediction_rate": "18.57%"
          }
        },
        {
          "config": {
            "table_size": 512,
            "initial_state": "StronglyTaken"
          },
          "result": {
            "mispredictions": 1694,
            "count": 8431,
            "correct": 6737,
            "accuracy": "79.91%",
            "misprediction_rate": "20.09%"
          }
        },
        {
          "config": {
            "table_size": 1024,
            "initial_state": "StronglyNotTaken"
          },
          "result": {
            "mispredictions": 1401,
            "count": 8431,
            "correct": 7030,
            "accuracy": "83.38%",
            "misprediction_rate": "16.62%"
          }
        },
        {
          "config": {
            "table_size": 1024,
            "initial_state": "WeaklyNotTaken"
          },
          "result": {
            "mispredictions": 1355,
            "count": 8431,
            "correct": 7076,
            "accuracy": "83.93%",
            "misprediction_rate": "16.07%"
          }
        },
        {
          "config": {
            "table_size": 1024,
            "initial_state": "WeaklyTaken"
          },
          "result": {
            "mispredictions": 1502,
            "count": 8431,
            "correct": 6929,
            "accuracy": "82.18%",
            "misprediction_rate": "17.82%"
          }
        },
        {
          "config": {
            "table_size": 1024,
            "initial_state": "StronglyTaken"
          },
          "result": {
            "mispredictions": 1675,
            "count": 8431,
            "correct": 6756,
            "accuracy": "80.13%",
            "misprediction_rate": "19.87%"
          }
        },
        {
          "config": {
            "table_size": 2048,
            "initial_state": "StronglyNotTaken"
          },
          "result": {
            "mispredictions": 1382,
            "count": 8431,
            "correct": 7049,
            "accuracy": "83.61%",
            "misprediction_rate": "16.39%"
          }
        },
        {
          "config": {
            "table_size": 2048,
            "initial_state": "WeaklyNotTaken"
          },
          "result": {
            "mispredictions": 1313,
            "count": 8431,
            "correct": 7118,
            "accuracy": "84.43%",
            "misprediction_rate": "15.57%"
          }
        },
        {
          "config": {
            "table_size": 2048,
            "initial_state": "WeaklyTaken"
          },
          "result": {
            "mispredictions": 1512,
            "count": 8431,
            "correct": 6919,
            "accuracy": "82.07%",
            "misprediction_rate": "17.93%"
          }
        },
        {
          "config": {
            "table_size": 2048,
            "initial_state": "StronglyTaken"
          },
          "result": {
            "mispredictions": 1717,
            "count": 8431,
            "correct": 6714,
            "accuracy": "79.63%",
            "misprediction_rate": "20.37%"
          }
        },
        {
          "config": {
            "table_size": 4096,
            "initial_state": "StronglyNotTaken"
          },
          "result": {
            "mispredictions": 1360,
            "count": 8431,
            "correct": 7071,
            "accuracy": "83.87%",
            "misprediction_rate": "16.13%"
          }
        },
        {
          "config": {
            "table_size": 4096,
            "initial_state": "WeaklyNotTaken"
          },
          "result": {
            "mispredictions": 1280,
            "count": 8431,
            "correct": 7151,
            "accuracy": "84.82%",
            "misprediction_rate": "15.18%"
          }
        },
        {
          "config": {
            "table_size": 4096,
            "initial_state": "WeaklyTaken"
          },
          "result": {
            "mispredictions": 1508,
            "count": 8431,
            "correct": 6923,
            "accuracy": "82.11%",
            "misprediction_rate": "17.89%"
          }
        },
        {
          "config": {
            "table_size": 4096,
            "initial_state": "StronglyTaken"
          },
          "result": {
            "mispredictions": 1738,
            "count": 8431,
            "correct": 6693,
            "accuracy": "79.39%",
            "misprediction_rate": "20.61%"
          }
        }
      ]
    },
    {
      "max_lines": 100000,
      "stats": [
        {
          "config": {
            "table_size": 512,
            "initial_state": "StronglyNotTaken"
          },
          "result": {
            "mispredictions": 7630,
            "count": 80885,
            "correct": 73255,
            "accuracy": "90.57%",
            "misprediction_rate": "9.43%"
          }
        },
        {
          "config": {
            "table_size": 512,
            "initial_state": "WeaklyNotTaken"
          },
          "result": {
            "mispredictions": 7615,
            "count": 80885,
            "correct": 73270,
            "accuracy": "90.59%",
            "misprediction_rate": "9.41%"
          }
        },
        {
          "config": {
            "table_size": 512,
            "initial_state": "WeaklyTaken"
          },
          "result": {
            "mispredictions": 7758,
            "count": 80885,
            "correct": 73127,
            "accuracy": "90.41%",
            "misprediction_rate": "9.59%"
          }
        },
        {
          "config": {
            "table_size": 512,
            "initial_state": "StronglyTaken"
          },
          "result": {
            "mispredictions": 7947,
            "count": 80885,
            "correct": 72938,
            "accuracy": "90.17%",
            "misprediction_rate": "9.83%"
          }
        },
        {
          "config": {
            "table_size": 1024,
            "initial_state": "StronglyNotTaken"
          },
          "result": {
            "mispredictions": 6836,
            "count": 80885,
            "correct": 74049,
            "accuracy": "91.55%",
            "misprediction_rate": "8.45%"
          }
        },
        {
          "config": {
            "table_size": 1024,
            "initial_state": "WeaklyNotTaken"
          },
          "result": {
            "mispredictions": 6767,
            "count": 80885,
            "correct": 74118,
            "accuracy": "91.63%",
            "misprediction_rate": "8.37%"
          }
        },
        {
          "config": {
            "table_size": 1024,
            "initial_state": "WeaklyTaken"
          },
          "result": {
            "mispredictions": 6987,
            "count": 80885,
            "correct": 73898,
            "accuracy": "91.36%",
            "misprediction_rate": "8.64%"
          }
        },
        {
          "config": {
            "table_size": 1024,
            "initial_state": "StronglyTaken"
          },
          "result": {
            "mispredictions": 7334,
            "count": 80885,
            "correct": 73551,
            "accuracy": "90.93%",
            "misprediction_rate": "9.07%"
          }
        },
        {
          "config": {
            "table_size": 2048,
            "initial_state": "StronglyNotTaken"
          },
          "result": {
            "mispredictions": 6433,
            "count": 80885,
            "correct": 74452,
            "accuracy": "92.05%",
            "misprediction_rate": "7.95%"
          }
        },
        {
          "config": {
            "table_size": 2048,
            "initial_state": "WeaklyNotTaken"
          },
          "result": {
            "mispredictions": 6303,
            "count": 80885,
            "correct": 74582,
            "accuracy": "92.21%",
            "misprediction_rate": "7.79%"
          }
        },
        {
          "config": {
            "table_size": 2048,
            "initial_state": "WeaklyTaken"
          },
          "result": {
            "mispredictions": 6681,
            "count": 80885,
            "correct": 74204,
            "accuracy": "91.74%",
            "misprediction_rate": "8.26%"
          }
        },
        {
          "config": {
            "table_size": 2048,
            "initial_state": "StronglyTaken"
          },
          "result": {
            "mispredictions": 7197,
            "count": 80885,
            "correct": 73688,
            "accuracy": "91.10%",
            "misprediction_rate": "8.90%"
          }
        },
        {
          "config": {
            "table_size": 4096,
            "initial_state": "StronglyNotTaken"
          },
          "result": {
            "mispredictions": 6112,
            "count": 80885,
            "correct": 74773,
            "accuracy": "92.44%",
            "misprediction_rate": "7.56%"
          }
        },
        {
          "config": {
            "table_size": 4096,
            "initial_state": "WeaklyNotTaken"
          },
          "result": {
            "mispredictions": 5899,
            "count": 80885,
            "correct": 74986,
            "accuracy": "92.71%",
            "misprediction_rate": "7.29%"
          }
        },
        {
          "config": {
            "table_size": 4096,
            "initial_state": "WeaklyTaken"
          },
          "result": {
            "mispredictions": 6424,
            "count": 80885,
            "correct": 74461,
            "accuracy": "92.06%",
            "misprediction_rate": "7.94%"
          }
        },
        {
          "config": {
            "table_size": 4096,
            "initial_state": "StronglyTaken"
          },
          "result": {
            "mispredictions": 7096,
            "count": 80885,
            "correct": 73789,
            "accuracy": "91.23%",
            "misprediction_rate": "8.77%"
          }
        }
      ]
    },
    {
      "max_lines": 1000000,
      "stats": [
        {
          "config": {
            "table_size": 512,
            "initial_state": "StronglyNotTaken"
          },
          "result": {
            "mispredictions": 105074,
            "count": 851302,
            "correct": 746228,
            "accuracy": "87.66%",
            "misprediction_rate": "12.34%"
          }
        },
        {
          "config": {
            "table_size": 512,
            "initial_state": "WeaklyNotTaken"
          },
          "result": {
            "mispredictions": 105057,
            "count": 851302,
            "correct": 746245,
            "accuracy": "87.66%",
            "misprediction_rate": "12.34%"
          }
        },
        {
          "config": {
            "table_size": 512,
            "initial_state": "WeaklyTaken"
          },
          "result": {
            "mispredictions": 105199,
            "count": 851302,
            "correct": 746103,
            "accuracy": "87.64%",
            "misprediction_rate": "12.36%"
          }
        },
        {
          "config": {
            "table_size": 512,
            "initial_state": "StronglyTaken"
          },
          "result": {
            "mispredictions": 105388,
            "count": 851302,
            "correct": 745914,
            "accuracy": "87.62%",
            "misprediction_rate": "12.38%"
          }
        },
        {
          "config": {
            "table_size": 1024,
            "initial_state": "StronglyNotTaken"
          },
          "result": {
            "mispredictions": 102570,
            "count": 851302,
            "correct": 748732,
            "accuracy": "87.95%",
            "misprediction_rate": "12.05%"
          }
        },
        {
          "config": {
            "table_size": 1024,
            "initial_state": "WeaklyNotTaken"
          },
          "result": {
            "mispredictions": 102502,
            "count": 851302,
            "correct": 748800,
            "accuracy": "87.96%",
            "misprediction_rate": "12.04%"
          }
        },
        {
          "config": {
            "table_size": 1024,
            "initial_state": "WeaklyTaken"
          },
          "result": {
            "mispredictions": 102726,
            "count": 851302,
            "correct": 748576,
            "accuracy": "87.93%",
            "misprediction_rate": "12.07%"
          }
        },
        {
          "config": {
            "table_size": 1024,
            "initial_state": "StronglyTaken"
          },
          "result": {
            "mispredictions": 103093,
            "count": 851302,
            "correct": 748209,
            "accuracy": "87.89%",
            "misprediction_rate": "12.11%"
          }
        },
        {
          "config": {
            "table_size": 2048,
            "initial_state": "StronglyNotTaken"
          },
          "result": {
            "mispredictions": 100696,
            "count": 851302,
            "correct": 750606,
            "accuracy": "88.17%",
            "misprediction_rate": "11.83%"
          }
        },
        {
          "config": {
            "table_size": 2048,
            "initial_state": "WeaklyNotTaken"
          },
          "result": {
            "mispredictions": 100504,
            "count": 851302,
            "correct": 750798,
            "accuracy": "88.19%",
            "misprediction_rate": "11.81%"
          }
        },
        {
          "config": {
            "table_size": 2048,
            "initial_state": "WeaklyTaken"
          },
          "result": {
            "mispredictions": 100933,
            "count": 851302,
            "correct": 750369,
            "accuracy": "88.14%",
            "misprediction_rate": "11.86%"
          }
        },
        {
          "config": {
            "table_size": 2048,
            "initial_state": "StronglyTaken"
          },
          "result": {
            "mispredictions": 101544,
            "count": 851302,
            "correct": 749758,
            "accuracy": "88.07%",
            "misprediction_rate": "11.93%"
          }
        },
        {
          "config": {
            "table_size": 4096,
            "initial_state": "StronglyNotTaken"
          },
          "result": {
            "mispredictions": 99981,
            "count": 851302,
            "correct": 751321,
            "accuracy": "88.26%",
            "misprediction_rate": "11.74%"
          }
        },
        {
          "config": {
            "table_size": 4096,
            "initial_state": "WeaklyNotTaken"
          },
          "result": {
            "mispredictions": 99577,
            "count": 851302,
            "correct": 751725,
            "accuracy": "88.30%",
            "misprediction_rate": "11.70%"
          }
        },
        {
          "config": {
            "table_size": 4096,
            "initial_state": "WeaklyTaken"
          },
          "result": {
            "mispredictions": 100190,
            "count": 851302,
            "correct": 751112,
            "accuracy": "88.23%",
            "misprediction_rate": "11.77%"
          }
        },
        {
          "config": {
            "table_size": 4096,
            "initial_state": "StronglyTaken"
          },
          "result": {
            "mispredictions": 101126,
            "count": 851302,
            "correct": 750176,
            "accuracy": "88.12%",
            "misprediction_rate": "11.88%"
          }
        }
      ]
    },
    {
      "max_lines": -1,
      "stats": [
        {
          "config": {
            "table_size": 512,
            "initial_state": "StronglyNotTaken"
          },
          "result": {
            "mispredictions": 1657822,
            "count": 13134996,
            "correct": 11477174,
            "accuracy": "87.38%",
            "misprediction_rate": "12.62%"
          }
        },
        {
          "config": {
            "table_size": 512,
            "initial_state": "WeaklyNotTaken"
          },
          "result": {
            "mispredictions": 1657805,
            "count": 13134996,
            "correct": 11477191,
            "accuracy": "87.38%",
            "misprediction_rate": "12.62%"
          }
        },
        {
          "config": {
            "table_size": 512,
            "initial_state": "WeaklyTaken"
          },
          "result": {
            "mispredictions": 1657947,
            "count": 13134996,
            "correct": 11477049,
            "accuracy": "87.38%",
            "misprediction_rate": "12.62%"
          }
        },
        {
          "config": {
            "table_size": 512,
            "initial_state": "StronglyTaken"
          },
          "result": {
            "mispredictions": 1658136,
            "count": 13134996,
            "correct": 11476860,
            "accuracy": "87.38%",
            "misprediction_rate": "12.62%"
          }
        },
        {
          "config": {
            "table_size": 1024,
            "initial_state": "StronglyNotTaken"
          },
          "result": {
            "mispredictions": 1623762,
            "count": 13134996,
            "correct": 11511234,
            "accuracy": "87.64%",
            "misprediction_rate": "12.36%"
          }
        },
        {
          "config": {
            "table_size": 1024,
            "initial_state": "WeaklyNotTaken"
          },
          "result": {
            "mispredictions": 1623695,
            "count": 13134996,
            "correct": 11511301,
            "accuracy": "87.64%",
            "misprediction_rate": "12.36%"
          }
        },
        {
          "config": {
            "table_size": 1024,
            "initial_state": "WeaklyTaken"
          },
          "result": {
            "mispredictions": 1623922,
            "count": 13134996,
            "correct": 11511074,
            "accuracy": "87.64%",
            "misprediction_rate": "12.36%"
          }
        },
        {
          "config": {
            "table_size": 1024,
            "initial_state": "StronglyTaken"
          },
          "result": {
            "mispredictions": 1624289,
            "count": 13134996,
            "correct": 11510707,
            "accuracy": "87.63%",
            "misprediction_rate": "12.37%"
          }
        },
        {
          "config": {
            "table_size": 2048,
            "initial_state": "StronglyNotTaken"
          },
          "result": {
            "mispredictions": 1585824,
            "count": 13134996,
            "correct": 11549172,
            "accuracy": "87.93%",
            "misprediction_rate": "12.07%"
          }
        },
        {
          "config": {
            "table_size": 2048,
            "initial_state": "WeaklyNotTaken"
          },
          "result": {
            "mispredictions": 1585628,
            "count": 13134996,
            "correct": 11549368,
            "accuracy": "87.93%",
            "misprediction_rate": "12.07%"
          }
        },
        {
          "config": {
            "table_size": 2048,
            "initial_state": "WeaklyTaken"
          },
          "result": {
            "mispredictions": 1586051,
            "count": 13134996,
            "correct": 11548945,
            "accuracy": "87.92%",
            "misprediction_rate": "12.08%"
          }
        },
        {
          "config": {
            "table_size": 2048,
            "initial_state": "StronglyTaken"
          },
          "result": {
            "mispredictions": 1586665,
            "count": 13134996,
            "correct": 11548331,
            "accuracy": "87.92%",
            "misprediction_rate": "12.08%"
          }
        },
        {
          "config": {
            "table_size": 4096,
            "initial_state": "StronglyNotTaken"
          },
          "result": {
            "mispredictions": 1572601,
            "count": 13134996,
            "correct": 11562395,
            "accuracy": "88.03%",
            "misprediction_rate": "11.97%"
          }
        },
        {
          "config": {
            "table_size": 4096,
            "initial_state": "WeaklyNotTaken"
          },
          "result": {
            "mispredictions": 1572156,
            "count": 13134996,
            "correct": 11562840,
            "accuracy": "88.03%",
            "misprediction_rate": "11.97%"
          }
        },
        {
          "config": {
            "table_size": 4096,
            "initial_state": "WeaklyTaken"
          },
          "result": {
            "mispredictions": 1572757,
            "count": 13134996,
            "correct": 11562239,
            "accuracy": "88.03%",
            "misprediction_rate": "11.97%"
          }
        },
        {
          "config": {
            "table_size": 4096,
            "initial_state": "StronglyTaken"
          },
          "result": {
            "mispredictions": 1573717,
            "count": 13134996,
            "correct": 11561279,
            "accuracy": "88.02%",
            "misprediction_rate": "11.98%"
          }
        }
      ]
    }
  ]
}